{
  "ber": 7.43797603046595e-06,
  "ber_zero_error_upper_bound": NaN,
  "bit_errors": 85,
  "bler": 0.0002604166666666,
  "bler_zero_error_upper_bound": NaN,
  "block_errors": 1,
  "checkpoint_path": "/scratch/rsadve1/Extended_UPAIR_Narval_b32m16_portable/TWC_plots_comprehensive/runs_rx16/seed7/1dmrs/main_d256_b4_r2/checkpoints/best.weights.h5",
  "chunk_batches_requested": 20,
  "chunk_curves_path": "/home/rsadve1/scratch/Extended_UPAIR_Narval_b32m16_portable/_final_u3_baseline_chunks/main_d256_b4_r2_u3_perfect_csi_lmmse_ebnom1p0_chunk0092_m8_b20/metrics/curves.csv",
  "chunk_idx": 92,
  "chunk_output_dir": "/home/rsadve1/scratch/Extended_UPAIR_Narval_b32m16_portable/_final_u3_baseline_chunks/main_d256_b4_r2_u3_perfect_csi_lmmse_ebnom1p0_chunk0092_m8_b20",
  "data_elapsed_s": 57.37036984995939,
  "dmrs_case": "1dmrs",
  "ebno_db": -1.0,
  "evaluation_seed": 10887310,
  "gpu_mem_gib": 0.0875845327973365,
  "gpu_peak_gib": 0.2734438236802816,
  "mc_stop_reason": "global_stop",
  "nmse": 0.0,
  "num_batches_run": 20,
  "num_bits": 11427840,
  "num_blocks": 3840,
  "num_users": 3,
  "point_elapsed_s": 186.72450515197124,
  "receiver": "perfect_csi_lmmse",
  "receiver_elapsed_s": 117.90923135040794,
  "receiver_microbatch_size": 8,
  "receiver_ms_per_batch": 5895.461567520397,
  "receiver_ms_per_frame": 30.705528997502068,
  "reliable_ber": false,
  "reliable_bler": false,
  "seed": 7,
  "target_bler_floor": 1e-05,
  "training_seed": 7,
  "variant": "main_d256_b4_r2"
}